modelz/__init__.py
modelz/args.py
modelz/client.py
modelz/cmd.py
modelz/env.py
modelz/gradio_client.py
modelz/serde.py
modelz/__version__.py
modelz_py-0.3.3.dist-info/entry_points.txt
modelz_py-0.3.3.dist-info/WHEEL
modelz_py-0.3.3.dist-info/METADATA
modelz_py-0.3.3.dist-info/licenses/LICENSE
modelz_py-0.3.3.dist-info/RECORD
