Metadata-Version: 2.1
Name: modelz-py
Version: 0.3.3
Summary: machine learning models
License: Apache-2.0
Keywords: machine learning,deep learning
Author-email: TensorChord <modelz-support@tensorchord.ai>
Requires-Python: >=3.7
Classifier: Environment :: GPU
Classifier: Intended Audience :: Developers
Classifier: Topic :: Scientific/Engineering :: Artificial Intelligence
Requires-Dist: gradio-client>=0.2.0
Requires-Dist: httpx>=0.23.3
Requires-Dist: msgpack>=1.0.4
Requires-Dist: rich>=12.6.0
Requires-Dist: typer[all]>=0.7.0
